[
  {
    "keyword": "Feature",
    "name": "Validating the Dashboard page",
    "line": 2,
    "id": "validating-the-dashboard-page",
    "tags": [
      {
        "name": "@Test",
        "line": 1
      }
    ],
    "uri": "Dashboardpage.feature",
    "elements": [
      {
        "id": "validating-the-dashboard-page;verify-the-fund-and-investor",
        "keyword": "Scenario",
        "line": 12,
        "name": "Verify the fund and investor",
        "tags": [
          {
            "name": "@Test",
            "line": 1
          }
        ],
        "type": "scenario",
        "steps": [
          {
            "arguments": [],
            "keyword": "Given ",
            "line": 5,
            "name": "The user lands on the authentication page",
            "result": {
              "status": "passed",
              "duration": 1457000000
            }
          },
          {
            "arguments": [],
            "keyword": "When ",
            "line": 6,
            "name": "User enter the user name or mailid and password",
            "result": {
              "status": "passed",
              "duration": 3466000000
            }
          },
          {
            "arguments": [],
            "keyword": "And ",
            "line": 7,
            "name": "Clicks on the sign in button",
            "result": {
              "status": "passed",
              "duration": 1498000000
            }
          },
          {
            "arguments": [],
            "keyword": "Then ",
            "line": 8,
            "name": "Verify user should be successfully navigated to home page",
            "result": {
              "status": "passed",
              "duration": 1535000000
            }
          },
          {
            "arguments": [],
            "keyword": "When ",
            "line": 9,
            "name": "User selects the Investor from LPS drop-down",
            "result": {
              "status": "passed",
              "duration": 217000000
            }
          },
          {
            "arguments": [],
            "keyword": "And ",
            "line": 10,
            "name": "User selects the fund from vehicle drop-down",
            "result": {
              "status": "passed",
              "duration": 278000000
            }
          },
          {
            "arguments": [],
            "keyword": "When ",
            "line": 13,
            "name": "The user hits the api request for the base data",
            "result": {
              "status": "passed",
              "duration": 644000000
            }
          },
          {
            "arguments": [],
            "keyword": "Then ",
            "line": 14,
            "name": "Verify partner logo is displayed on the left panel",
            "result": {
              "status": "passed",
              "duration": 15000000
            }
          }
        ]
      },
      {
        "id": "validating-the-dashboard-page;verify-if-the-timeline-widget-is-displayed-on-the-dashboard-page",
        "keyword": "Scenario",
        "line": 16,
        "name": "Verify if the timeline widget is displayed on the dashboard page",
        "tags": [
          {
            "name": "@Test",
            "line": 1
          }
        ],
        "type": "scenario",
        "steps": [
          {
            "arguments": [],
            "keyword": "Given ",
            "line": 5,
            "name": "The user lands on the authentication page",
            "result": {
              "status": "passed",
              "duration": 956000000
            }
          },
          {
            "arguments": [],
            "keyword": "When ",
            "line": 6,
            "name": "User enter the user name or mailid and password",
            "result": {
              "status": "passed",
              "duration": 47301000000
            }
          },
          {
            "arguments": [],
            "keyword": "And ",
            "line": 7,
            "name": "Clicks on the sign in button",
            "result": {
              "status": "passed",
              "duration": 1493000000
            }
          },
          {
            "arguments": [],
            "keyword": "Then ",
            "line": 8,
            "name": "Verify user should be successfully navigated to home page",
            "result": {
              "status": "passed",
              "duration": 939000000
            }
          },
          {
            "arguments": [],
            "keyword": "When ",
            "line": 9,
            "name": "User selects the Investor from LPS drop-down",
            "result": {
              "status": "passed",
              "duration": 228000000
            }
          },
          {
            "arguments": [],
            "keyword": "And ",
            "line": 10,
            "name": "User selects the fund from vehicle drop-down",
            "result": {
              "status": "passed",
              "duration": 341000000
            }
          },
          {
            "arguments": [],
            "keyword": "When ",
            "line": 17,
            "name": "The user hits the api request for the dashboard",
            "result": {
              "status": "passed",
              "duration": 175000000
            }
          },
          {
            "arguments": [],
            "keyword": "Then ",
            "line": 18,
            "name": "Verify timeline widget is displayed",
            "result": {
              "status": "passed",
              "duration": 21000000
            }
          },
          {
            "arguments": [],
            "keyword": "And ",
            "line": 19,
            "name": "Verify the investment start date in the timeline",
            "result": {
              "status": "passed",
              "duration": 10000000
            }
          },
          {
            "arguments": [],
            "keyword": "And ",
            "line": 20,
            "name": "Verify the liquidation end date in the timeline",
            "result": {
              "status": "passed",
              "duration": 11000000
            }
          },
          {
            "arguments": [],
            "keyword": "When ",
            "line": 21,
            "name": "User hover on the events in the timeline",
            "result": {
              "status": "passed",
              "duration": 3166000000
            }
          },
          {
            "arguments": [],
            "keyword": "Then ",
            "line": 22,
            "name": "A tooltip should be visible",
            "result": {
              "status": "passed",
              "duration": 23000000
            }
          }
        ]
      },
      {
        "id": "validating-the-dashboard-page;verify-if-the-banner-widget-is-displayed-on-the-dashboard-page",
        "keyword": "Scenario",
        "line": 24,
        "name": "Verify if the Banner widget is displayed on the dashboard page",
        "tags": [
          {
            "name": "@Test",
            "line": 1
          }
        ],
        "type": "scenario",
        "steps": [
          {
            "arguments": [],
            "keyword": "Given ",
            "line": 5,
            "name": "The user lands on the authentication page",
            "result": {
              "status": "passed",
              "duration": 1228000000
            }
          },
          {
            "arguments": [],
            "keyword": "When ",
            "line": 6,
            "name": "User enter the user name or mailid and password",
            "result": {
              "status": "passed",
              "duration": 9954000000
            }
          },
          {
            "arguments": [],
            "keyword": "And ",
            "line": 7,
            "name": "Clicks on the sign in button",
            "result": {
              "status": "passed",
              "duration": 1408000000
            }
          },
          {
            "arguments": [],
            "keyword": "Then ",
            "line": 8,
            "name": "Verify user should be successfully navigated to home page",
            "result": {
              "status": "passed",
              "duration": 916000000
            }
          },
          {
            "arguments": [],
            "keyword": "When ",
            "line": 9,
            "name": "User selects the Investor from LPS drop-down",
            "result": {
              "status": "passed",
              "duration": 212000000
            }
          },
          {
            "arguments": [],
            "keyword": "And ",
            "line": 10,
            "name": "User selects the fund from vehicle drop-down",
            "result": {
              "status": "passed",
              "duration": 267000000
            }
          },
          {
            "arguments": [],
            "keyword": "When ",
            "line": 25,
            "name": "The user hits the api request for the dashboard",
            "result": {
              "status": "passed",
              "duration": 510000000
            }
          },
          {
            "arguments": [],
            "keyword": "And ",
            "line": 26,
            "name": "Banner Widget is displayed",
            "result": {
              "status": "passed",
              "duration": 13000000
            }
          },
          {
            "arguments": [],
            "keyword": "When ",
            "line": 27,
            "name": "User click on the banner widget it redirected to a respective url",
            "result": {
              "status": "passed",
              "duration": 2120000000
            }
          }
        ]
      },
      {
        "id": "validating-the-dashboard-page;verify-if-the-investment-widget-is-displayed-on-the-dashboard-page",
        "keyword": "Scenario",
        "line": 29,
        "name": "Verify if the investment widget is displayed on the dashboard page",
        "tags": [
          {
            "name": "@Test",
            "line": 1
          }
        ],
        "type": "scenario",
        "steps": [
          {
            "arguments": [],
            "keyword": "Given ",
            "line": 5,
            "name": "The user lands on the authentication page",
            "result": {
              "status": "passed",
              "duration": 1317000000
            }
          },
          {
            "arguments": [],
            "keyword": "When ",
            "line": 6,
            "name": "User enter the user name or mailid and password",
            "result": {
              "status": "passed",
              "duration": 18269000000
            }
          },
          {
            "arguments": [],
            "keyword": "And ",
            "line": 7,
            "name": "Clicks on the sign in button",
            "result": {
              "status": "passed",
              "duration": 1435000000
            }
          },
          {
            "arguments": [],
            "keyword": "Then ",
            "line": 8,
            "name": "Verify user should be successfully navigated to home page",
            "result": {
              "status": "passed",
              "duration": 897000000
            }
          },
          {
            "arguments": [],
            "keyword": "When ",
            "line": 9,
            "name": "User selects the Investor from LPS drop-down",
            "result": {
              "status": "passed",
              "duration": 234000000
            }
          },
          {
            "arguments": [],
            "keyword": "And ",
            "line": 10,
            "name": "User selects the fund from vehicle drop-down",
            "result": {
              "status": "passed",
              "duration": 282000000
            }
          },
          {
            "arguments": [],
            "keyword": "When ",
            "line": 30,
            "name": "The user hits the api request for the dashboard",
            "result": {
              "status": "passed",
              "duration": 209000000
            }
          },
          {
            "arguments": [],
            "keyword": "And ",
            "line": 31,
            "name": "Investment Widget is displayed",
            "result": {
              "status": "passed",
              "duration": 12000000
            }
          },
          {
            "arguments": [],
            "keyword": "Then ",
            "line": 32,
            "name": "Verify the investment widgets and their respective graphs",
            "result": {
              "status": "passed",
              "duration": 10000000
            }
          }
        ]
      },
      {
        "id": "validating-the-dashboard-page;verify-if-the-performance-widget-is-displayed-on-the-dashboard-page",
        "keyword": "Scenario",
        "line": 34,
        "name": "Verify if the performance widget is displayed on the dashboard page",
        "tags": [
          {
            "name": "@Test",
            "line": 1
          }
        ],
        "type": "scenario",
        "steps": [
          {
            "arguments": [],
            "keyword": "Given ",
            "line": 5,
            "name": "The user lands on the authentication page",
            "result": {
              "status": "passed",
              "duration": 1365000000
            }
          },
          {
            "arguments": [],
            "keyword": "When ",
            "line": 6,
            "name": "User enter the user name or mailid and password",
            "result": {
              "status": "passed",
              "duration": 13411000000
            }
          },
          {
            "arguments": [],
            "keyword": "And ",
            "line": 7,
            "name": "Clicks on the sign in button",
            "result": {
              "status": "passed",
              "duration": 1625000000
            }
          },
          {
            "arguments": [],
            "keyword": "Then ",
            "line": 8,
            "name": "Verify user should be successfully navigated to home page",
            "result": {
              "status": "passed",
              "duration": 1301000000
            }
          },
          {
            "arguments": [],
            "keyword": "When ",
            "line": 9,
            "name": "User selects the Investor from LPS drop-down",
            "result": {
              "status": "passed",
              "duration": 236000000
            }
          },
          {
            "arguments": [],
            "keyword": "And ",
            "line": 10,
            "name": "User selects the fund from vehicle drop-down",
            "result": {
              "status": "passed",
              "duration": 305000000
            }
          },
          {
            "arguments": [],
            "keyword": "When ",
            "line": 35,
            "name": "The user hits the api request for the dashboard",
            "result": {
              "status": "passed",
              "duration": 475000000
            }
          },
          {
            "arguments": [],
            "keyword": "And ",
            "line": 36,
            "name": "Performance Widget is displayed",
            "result": {
              "status": "passed",
              "duration": 18000000
            }
          },
          {
            "arguments": [],
            "keyword": "Then ",
            "line": 37,
            "name": "Details on the Performance widget are verified",
            "result": {
              "status": "failed",
              "error_message": "TypeError: Cannot read properties of null (reading 'toFixed')\n    at Context.eval (cypress/integration/examples/BDD/Dashboardpage/Dashboardpage_stepdef.js:161:43)\n    at Context.resolveAndRunStepDefinition (node_modules/cypress-cucumber-preprocessor/lib/resolveStepDefinition.js:193:0)\n    at Context.eval (node_modules/cypress-cucumber-preprocessor/lib/createTestFromScenario.js:27:0)\nFrom previous event:\n    at Context.thenFn (https://investorportal.qa.ace-alternatives.com/__cypress/runner/cypress_runner.js:139307:63)\n    at Context.then (https://investorportal.qa.ace-alternatives.com/__cypress/runner/cypress_runner.js:139587:21)\n    at wrapped (https://investorportal.qa.ace-alternatives.com/__cypress/runner/cypress_runner.js:156314:19)\n    at <unknown> (https://investorportal.qa.ace-alternatives.com/__cypress/runner/cypress_runner.js:155103:15)\nFrom previous event:\n    at CommandQueue.runCommand (https://investorportal.qa.ace-alternatives.com/__cypress/runner/cypress_runner.js:155069:8)\n    at next (https://investorportal.qa.ace-alternatives.com/__cypress/runner/cypress_runner.js:155267:19)\n    at <unknown> (https://investorportal.qa.ace-alternatives.com/__cypress/runner/cypress_runner.js:155289:16)"
            }
          }
        ]
      },
      {
        "id": "validating-the-dashboard-page;verify-user-navigates-to-the-insights-page-upon-clicking-on-the-see-details-links-from-the-performance-widget",
        "keyword": "Scenario",
        "line": 39,
        "name": "Verify user navigates to the insights page upon clicking on the see details links from the performance widget",
        "tags": [
          {
            "name": "@Test",
            "line": 1
          }
        ],
        "type": "scenario",
        "steps": [
          {
            "arguments": [],
            "keyword": "Given ",
            "line": 5,
            "name": "The user lands on the authentication page",
            "result": {
              "status": "passed",
              "duration": 1268000000
            }
          },
          {
            "arguments": [],
            "keyword": "When ",
            "line": 6,
            "name": "User enter the user name or mailid and password",
            "result": {
              "status": "passed",
              "duration": 33255000000
            }
          },
          {
            "arguments": [],
            "keyword": "And ",
            "line": 7,
            "name": "Clicks on the sign in button",
            "result": {
              "status": "passed",
              "duration": 1510000000
            }
          },
          {
            "arguments": [],
            "keyword": "Then ",
            "line": 8,
            "name": "Verify user should be successfully navigated to home page",
            "result": {
              "status": "passed",
              "duration": 1206000000
            }
          },
          {
            "arguments": [],
            "keyword": "When ",
            "line": 9,
            "name": "User selects the Investor from LPS drop-down",
            "result": {
              "status": "passed",
              "duration": 306000000
            }
          },
          {
            "arguments": [],
            "keyword": "And ",
            "line": 10,
            "name": "User selects the fund from vehicle drop-down",
            "result": {
              "status": "passed",
              "duration": 387000000
            }
          },
          {
            "arguments": [],
            "keyword": "When ",
            "line": 40,
            "name": "The user hits the api request for the dashboard",
            "result": {
              "status": "passed",
              "duration": 179000000
            }
          },
          {
            "arguments": [],
            "keyword": "And ",
            "line": 41,
            "name": "Performance Widget is displayed",
            "result": {
              "status": "passed",
              "duration": 22000000
            }
          },
          {
            "arguments": [],
            "keyword": "When ",
            "line": 42,
            "name": "Clicking on the see details link from the performance widget",
            "result": {
              "status": "passed",
              "duration": 195000000
            }
          },
          {
            "arguments": [],
            "keyword": "Then ",
            "line": 43,
            "name": "User should navigate to the Insights page successfully",
            "result": {
              "status": "passed",
              "duration": 22000000
            }
          }
        ]
      },
      {
        "id": "validating-the-dashboard-page;verify-if-the-capital-account-widget-is-displayed-on-the-dashboard-page",
        "keyword": "Scenario",
        "line": 45,
        "name": "Verify if the capital account widget is displayed on the dashboard page",
        "tags": [
          {
            "name": "@Test",
            "line": 1
          }
        ],
        "type": "scenario",
        "steps": [
          {
            "arguments": [],
            "keyword": "Given ",
            "line": 5,
            "name": "The user lands on the authentication page",
            "result": {
              "status": "passed",
              "duration": 1601000000
            }
          },
          {
            "arguments": [],
            "keyword": "When ",
            "line": 6,
            "name": "User enter the user name or mailid and password",
            "result": {
              "status": "passed",
              "duration": 1701000000
            }
          },
          {
            "arguments": [],
            "keyword": "And ",
            "line": 7,
            "name": "Clicks on the sign in button",
            "result": {
              "status": "passed",
              "duration": 1396000000
            }
          },
          {
            "arguments": [],
            "keyword": "Then ",
            "line": 8,
            "name": "Verify user should be successfully navigated to home page",
            "result": {
              "status": "passed",
              "duration": 935000000
            }
          },
          {
            "arguments": [],
            "keyword": "When ",
            "line": 9,
            "name": "User selects the Investor from LPS drop-down",
            "result": {
              "status": "passed",
              "duration": 261000000
            }
          },
          {
            "arguments": [],
            "keyword": "And ",
            "line": 10,
            "name": "User selects the fund from vehicle drop-down",
            "result": {
              "status": "passed",
              "duration": 370000000
            }
          },
          {
            "arguments": [],
            "keyword": "When ",
            "line": 46,
            "name": "The user hits the api request for the dashboard",
            "result": {
              "status": "passed",
              "duration": 500000000
            }
          },
          {
            "arguments": [],
            "keyword": "And ",
            "line": 47,
            "name": "Capital account Widget is displayed",
            "result": {
              "status": "passed",
              "duration": 27000000
            }
          },
          {
            "arguments": [],
            "keyword": "Then ",
            "line": 48,
            "name": "Details on the capital account widget are verified",
            "result": {
              "status": "failed",
              "error_message": "AssertionError: Timed out retrying after 5000ms: expected '[ <p.count.ng-star-inserted>, 5 more... ]' to have text '57,127,75119,682,325019,682,32516,451,6450', but the text was '57,127k19,682k019,682k16,451k0'\n    + expected - actual\n\n    -'57,127k19,682k019,682k16,451k0'\n    +'57,127,75119,682,325019,682,32516,451,6450'\n\n    at Context.eval (cypress/integration/examples/BDD/Dashboardpage/Dashboardpage_stepdef.js:192:5)\n    at Context.resolveAndRunStepDefinition (node_modules/cypress-cucumber-preprocessor/lib/resolveStepDefinition.js:193:0)\n    at Context.eval (node_modules/cypress-cucumber-preprocessor/lib/createTestFromScenario.js:27:0)"
            }
          }
        ]
      },
      {
        "id": "validating-the-dashboard-page;verify-user-navigates-to-the-capital-account-page-upon-clicking-on-the-see-details-links-from-the-capital-account-widget",
        "keyword": "Scenario",
        "line": 50,
        "name": "Verify user navigates to the capital account page upon clicking on the see details links from the capital account widget",
        "tags": [
          {
            "name": "@Test",
            "line": 1
          }
        ],
        "type": "scenario",
        "steps": [
          {
            "arguments": [],
            "keyword": "Given ",
            "line": 5,
            "name": "The user lands on the authentication page",
            "result": {
              "status": "passed",
              "duration": 2040000000
            }
          },
          {
            "arguments": [],
            "keyword": "When ",
            "line": 6,
            "name": "User enter the user name or mailid and password",
            "result": {
              "status": "passed",
              "duration": 2065000000
            }
          },
          {
            "arguments": [],
            "keyword": "And ",
            "line": 7,
            "name": "Clicks on the sign in button",
            "result": {
              "status": "passed",
              "duration": 1467000000
            }
          },
          {
            "arguments": [],
            "keyword": "Then ",
            "line": 8,
            "name": "Verify user should be successfully navigated to home page",
            "result": {
              "status": "passed",
              "duration": 959000000
            }
          },
          {
            "arguments": [],
            "keyword": "When ",
            "line": 9,
            "name": "User selects the Investor from LPS drop-down",
            "result": {
              "status": "passed",
              "duration": 275000000
            }
          },
          {
            "arguments": [],
            "keyword": "And ",
            "line": 10,
            "name": "User selects the fund from vehicle drop-down",
            "result": {
              "status": "passed",
              "duration": 397000000
            }
          },
          {
            "arguments": [],
            "keyword": "When ",
            "line": 51,
            "name": "The user hits the api request for the dashboard",
            "result": {
              "status": "passed",
              "duration": 187000000
            }
          },
          {
            "arguments": [],
            "keyword": "And ",
            "line": 52,
            "name": "Capital account Widget is displayed",
            "result": {
              "status": "passed",
              "duration": 124000000
            }
          },
          {
            "arguments": [],
            "keyword": "When ",
            "line": 53,
            "name": "Clicking on the see details link from the capital account widgets",
            "result": {
              "status": "passed",
              "duration": 156000000
            }
          },
          {
            "arguments": [],
            "keyword": "Then ",
            "line": 54,
            "name": "User should navigate to the capital account page successfully",
            "result": {
              "status": "passed",
              "duration": 22000000
            }
          }
        ]
      },
      {
        "id": "validating-the-dashboard-page;verify-the-upcoming-events-widgets",
        "keyword": "Scenario",
        "line": 57,
        "name": "Verify the upcoming events widgets",
        "tags": [
          {
            "name": "@Test",
            "line": 1
          }
        ],
        "type": "scenario",
        "steps": [
          {
            "arguments": [],
            "keyword": "Given ",
            "line": 5,
            "name": "The user lands on the authentication page",
            "result": {
              "status": "passed",
              "duration": 1604000000
            }
          },
          {
            "arguments": [],
            "keyword": "When ",
            "line": 6,
            "name": "User enter the user name or mailid and password",
            "result": {
              "status": "passed",
              "duration": 1781000000
            }
          },
          {
            "arguments": [],
            "keyword": "And ",
            "line": 7,
            "name": "Clicks on the sign in button",
            "result": {
              "status": "passed",
              "duration": 1359000000
            }
          },
          {
            "arguments": [],
            "keyword": "Then ",
            "line": 8,
            "name": "Verify user should be successfully navigated to home page",
            "result": {
              "status": "passed",
              "duration": 931000000
            }
          },
          {
            "arguments": [],
            "keyword": "When ",
            "line": 9,
            "name": "User selects the Investor from LPS drop-down",
            "result": {
              "status": "passed",
              "duration": 281000000
            }
          },
          {
            "arguments": [],
            "keyword": "And ",
            "line": 10,
            "name": "User selects the fund from vehicle drop-down",
            "result": {
              "status": "passed",
              "duration": 302000000
            }
          },
          {
            "arguments": [],
            "keyword": "When ",
            "line": 58,
            "name": "The user hits the api request for the upcoming events",
            "result": {
              "status": "passed",
              "duration": 621000000
            }
          },
          {
            "arguments": [],
            "keyword": "Then ",
            "line": 59,
            "name": "Upcoming event widget is displayed",
            "result": {
              "status": "passed",
              "duration": 33000000
            }
          },
          {
            "arguments": [],
            "keyword": "And ",
            "line": 60,
            "name": "Should contain the list of events",
            "result": {
              "status": "passed",
              "duration": 20000000
            }
          },
          {
            "arguments": [],
            "keyword": "When ",
            "line": 61,
            "name": "User click on any of the events",
            "result": {
              "status": "failed",
              "error_message": "AssertionError: Timed out retrying after 5000ms: Expected to find element: `eventsTile`, but never found it. Queried from:\n\n              > cy.get(div.eventsContainer)\n    at Context.eval (cypress/integration/examples/BDD/Dashboardpage/Dashboardpage_stepdef.js:245:30)"
            }
          },
          {
            "arguments": [],
            "keyword": "Then ",
            "line": 62,
            "name": "Verify the event is getting downloaded",
            "result": {
              "status": "skipped"
            }
          }
        ]
      },
      {
        "id": "validating-the-dashboard-page;verify-the-updates-widgets",
        "keyword": "Scenario",
        "line": 65,
        "name": "Verify the updates widgets",
        "tags": [
          {
            "name": "@Test",
            "line": 1
          }
        ],
        "type": "scenario",
        "steps": [
          {
            "arguments": [],
            "keyword": "Given ",
            "line": 5,
            "name": "The user lands on the authentication page",
            "result": {
              "status": "passed",
              "duration": 1551000000
            }
          },
          {
            "arguments": [],
            "keyword": "When ",
            "line": 6,
            "name": "User enter the user name or mailid and password",
            "result": {
              "status": "passed",
              "duration": 2552000000
            }
          },
          {
            "arguments": [],
            "keyword": "And ",
            "line": 7,
            "name": "Clicks on the sign in button",
            "result": {
              "status": "passed",
              "duration": 1583000000
            }
          },
          {
            "arguments": [],
            "keyword": "Then ",
            "line": 8,
            "name": "Verify user should be successfully navigated to home page",
            "result": {
              "status": "passed",
              "duration": 1506000000
            }
          },
          {
            "arguments": [],
            "keyword": "When ",
            "line": 9,
            "name": "User selects the Investor from LPS drop-down",
            "result": {
              "status": "passed",
              "duration": 308000000
            }
          },
          {
            "arguments": [],
            "keyword": "And ",
            "line": 10,
            "name": "User selects the fund from vehicle drop-down",
            "result": {
              "status": "passed",
              "duration": 380000000
            }
          },
          {
            "arguments": [],
            "keyword": "When ",
            "line": 66,
            "name": "The user hits the api request for the updates",
            "result": {
              "status": "passed",
              "duration": 434000000
            }
          },
          {
            "arguments": [],
            "keyword": "And ",
            "line": 67,
            "name": "Updates widget is verified",
            "result": {
              "status": "passed",
              "duration": 29000000
            }
          },
          {
            "arguments": [],
            "keyword": "When ",
            "line": 68,
            "name": "User click on last login",
            "result": {
              "status": "passed",
              "duration": 4000000
            }
          },
          {
            "arguments": [],
            "keyword": "Then ",
            "line": 69,
            "name": "Should contain list of updates for last login",
            "result": {
              "status": "passed",
              "duration": 31000000
            }
          },
          {
            "arguments": [],
            "keyword": "When ",
            "line": 70,
            "name": "User click on last month",
            "result": {
              "status": "passed",
              "duration": 5000000
            }
          },
          {
            "arguments": [],
            "keyword": "Then ",
            "line": 71,
            "name": "Should contain list of updates for last month",
            "result": {
              "status": "passed",
              "duration": 30000000
            }
          },
          {
            "arguments": [],
            "keyword": "When ",
            "line": 72,
            "name": "User clicks on any of the updates",
            "result": {
              "status": "passed",
              "duration": 211000000
            }
          },
          {
            "arguments": [],
            "keyword": "Then ",
            "line": 73,
            "name": "User should sucessfully navigate to the respective page",
            "result": {
              "status": "passed",
              "duration": 3000000
            }
          }
        ]
      },
      {
        "id": "validating-the-dashboard-page;verify-the-news-widgets",
        "keyword": "Scenario",
        "line": 76,
        "name": "Verify the news widgets",
        "tags": [
          {
            "name": "@Test",
            "line": 1
          }
        ],
        "type": "scenario",
        "steps": [
          {
            "arguments": [],
            "keyword": "Given ",
            "line": 5,
            "name": "The user lands on the authentication page",
            "result": {
              "status": "passed",
              "duration": 995000000
            }
          },
          {
            "arguments": [],
            "keyword": "When ",
            "line": 6,
            "name": "User enter the user name or mailid and password",
            "result": {
              "status": "passed",
              "duration": 2570000000
            }
          },
          {
            "arguments": [],
            "keyword": "And ",
            "line": 7,
            "name": "Clicks on the sign in button",
            "result": {
              "status": "passed",
              "duration": 1696000000
            }
          },
          {
            "arguments": [],
            "keyword": "Then ",
            "line": 8,
            "name": "Verify user should be successfully navigated to home page",
            "result": {
              "status": "passed",
              "duration": 1060000000
            }
          },
          {
            "arguments": [],
            "keyword": "When ",
            "line": 9,
            "name": "User selects the Investor from LPS drop-down",
            "result": {
              "status": "passed",
              "duration": 271000000
            }
          },
          {
            "arguments": [],
            "keyword": "And ",
            "line": 10,
            "name": "User selects the fund from vehicle drop-down",
            "result": {
              "status": "passed",
              "duration": 342000000
            }
          },
          {
            "arguments": [],
            "keyword": "When ",
            "line": 77,
            "name": "The user hits the api request for the news",
            "result": {
              "status": "passed",
              "duration": 882000000
            }
          },
          {
            "arguments": [],
            "keyword": "Then ",
            "line": 78,
            "name": "News widget is displayed",
            "result": {
              "status": "passed",
              "duration": 42000000
            }
          },
          {
            "arguments": [],
            "keyword": "And ",
            "line": 79,
            "name": "Should contain the list of news",
            "result": {
              "status": "passed",
              "duration": 32000000
            }
          },
          {
            "arguments": [],
            "keyword": "When ",
            "line": 80,
            "name": "User clicks on any of the news",
            "result": {
              "status": "passed",
              "duration": 176000000
            }
          },
          {
            "arguments": [],
            "keyword": "Then ",
            "line": 81,
            "name": "Verify user navigates to the external url",
            "result": {
              "status": "passed",
              "duration": 9000000
            }
          }
        ]
      }
    ]
  }
]